maptiler/cloud_cli/__init__.py
maptiler/cloud_cli/__main__.py
maptiler/cloud_cli/base.py
maptiler_cloud_cli-1.2.1.dist-info/METADATA
maptiler_cloud_cli-1.2.1.dist-info/WHEEL
maptiler_cloud_cli-1.2.1.dist-info/entry_points.txt
maptiler_cloud_cli-1.2.1.dist-info/RECORD
