Metadata-Version: 2.1
Name: maptiler-cloud-cli
Version: 1.2.1
Summary: CLI utility for MapTiler Cloud
Home-page: https://github.com/maptiler/maptiler-cloud-cli
License: MIT
Author: MapTiler
Author-email: info@maptiler.com
Requires-Python: >=3.8
Classifier: License :: OSI Approved :: MIT License
Classifier: Programming Language :: Python :: 3
Classifier: Programming Language :: Python :: 3.8
Classifier: Programming Language :: Python :: 3.9
Classifier: Programming Language :: Python :: 3.10
Classifier: Programming Language :: Python :: 3.11
Classifier: Programming Language :: Python :: 3.12
Requires-Dist: click (>=8.0,<9.0)
Requires-Dist: requests (>=2.26,<3.0)
Project-URL: Documentation, https://docs.maptiler.com/cloud/admin-api/
Project-URL: Repository, https://github.com/maptiler/maptiler-cloud-cli
